asm2d
