Metadata-Version: 1.1
Name: asm2d
Version: 0.2.2
Summary: An assembler for the 68112D microprocessor
Home-page: http://tapichu.github.com/asm2d/
Author: Eduardo Lopez Biagi
Author-email: eduardo.biagi@gmail.com
License: BSD
Keywords: asm2d 6811 68HC11 68112d assembler
Platform: UNKNOWN
Classifier: Development Status :: 3 - Alpha
Classifier: License :: OSI Approved :: BSD License
Classifier: Programming Language :: Python :: 2.7
Classifier: Topic :: Software Development :: Assemblers
